wcpan/acd/__init__.py
wcpan/acd/controller.py
wcpan.acd-1.2.0.dist-info/DESCRIPTION.rst
wcpan.acd-1.2.0.dist-info/METADATA
wcpan.acd-1.2.0.dist-info/RECORD
wcpan.acd-1.2.0.dist-info/WHEEL
wcpan.acd-1.2.0.dist-info/metadata.json
wcpan.acd-1.2.0.dist-info/top_level.txt
